phantom_snap
