Metadata-Version: 1.1
Name: phantom-snap
Version: 0.0.18
Summary: Render HTML to an image using PhantomJS with this library                   designed to scale for high volume continuous operation.
Home-page: https://github.com/istresearch/phantom-snap
Author: Andrew Carter
Author-email: andrew.carter@istresearch.com
License: MIT
Keywords: web,html,render,screenshot,phantomjs
Platform: UNKNOWN
Classifier: Intended Audience :: Developers
Classifier: Topic :: System
Classifier: Topic :: System :: Distributed Computing
Classifier: Topic :: Utilities
